<?xml version="1.0" encoding="UTF-8" ?>
<?xml-stylesheet type="text/xsl" href="../../plays.xsl"?>

<poem>
<title short="To the Queen">To the Queen</title>
<playwright>William Shakespeare</playwright>

<poembody>
<stanza>

<line>As the dial hand tells  o&#8217;er</line>
<line>The same hours it had before,</line>
<line>Circular account still lending,</line>
<line>So, most mighty Queen we pray,</line>
<line>Like the dial day by day</line>
<line>You may lead the seasons on,</line>
<line>Making new when old are gone,</line>
<line>That the babe which now is young</line>
<line>And hath yet no use of tongue</line>
<line>Many a Shrovetide here may bow</line>
<line>To that empress I do now,</line>
<line>That these children of these lords,</line>
<line>Sitting at your council boards,</line>
<line>May be grave and agèd seen</line>
<line>Of her that was their fathers&#8217; queen.</line>
<line>Once I wish this wish again,</line>
<line>Heaven subscribe it with &#8220;Amen&#8221;.</line>

</stanza>
</poembody>


<sourcedetails>
<source>PlayShakespeare.com</source>
<sourceurl>http://www.playshakespeare.com</sourceurl>
<copyright>2005-2012 by PlayShakespeare.com</copyright>
<version>3.1</version>
<license>GFDL License 1.3</license>
<licenseurl>http://www.gnu.org/copyleft/fdl.html</licenseurl>
<termsurl>http://www.playshakespeare.com/about-us</termsurl>
</sourcedetails>

</poem>